Workbook

Sheet Banco De Ingredientes
B2: Nome do Ingrediente | C2: Unidade de Compra (kg, g, litro, unidade) | D2: Quantidade na Embalagem | E2: Preço Pago | F2: Custo por unidade (1g ou 1ml)
B3: Farinha de Trigo | C3: g | D3: 1000 | E3: 5.5 | F3: =E3/D3 -> 0.0055
B4: Açúcar Refinado | C4: g | D4: 1000 | E4: 4.8 | F4: =E4/D4 -> 0.0048
B5: Chocolate em Pó 50% | C5: g | D5: 500 | E5: 15 | F5: =E5/D5 -> 0.03
B6: Chocolate Meio Amargo | C6: g | D6: 1000 | E6: 45 | F6: =E6/D6 -> 0.045
B7: Manteiga sem Sal | C7: g | D7: 200 | E7: 12 | F7: =E7/D7 -> 0.06
B8: Ovos | C8: unidade | D8: 12 | E8: 10 | F8: =E8/D8 -> 0.83333333
B9: Leite Condensado | C9: g | D9: 395 | E9: 6.5 | F9: =E9/D9 -> 0.016455696
B10: Creme de Leite | C10: g | D10: 200 | E10: 4 | F10: =E10/D10 -> 0.02
B11: Fermento em Pó | C11: g | D11: 100 | E11: 3.5 | F11: =E11/D11 -> 0.035
B12: Leite Integral | C12: ml | D12: 1000 | E12: 5 | F12: =E12/D12 -> 0.005
B13: Gelatina Incolor | C13: g | D13: 24 | E13: 4.5 | F13: =E13/D13 -> 0.1875
B14: Essência de Baunilha | C14: ml | D14: 30 | E14: 6 | F14: =E14/D14 -> 0.2

Sheet Ficha Técnica (A Receita)
B2: Nome da Receita | C2: Ingrediente | D2: Quantidade Usada na Receita | E2: Custo do Ingrediente na Receita
B3: Brownie | C3: Farinha de Trigo | D3: 200 | E3: =VLOOKUP(C3, 'Banco De Ingredientes'!B:F, 5, 0) * D3 -> 1.1
B4: Brownie | C4: Açúcar Refinado | D4: 300 | E4: =VLOOKUP(C4, 'Banco De Ingredientes'!B:F, 5, 0) * D4 -> 1.44
B5: Brownie | C5: Manteiga sem Sal | D5: 200 | E5: =VLOOKUP(C5, 'Banco De Ingredientes'!B:F, 5, 0) * D5 -> 12
B6: Brownie | C6: Chocolate em Pó 50% | D6: 150 | E6: =VLOOKUP(C6, 'Banco De Ingredientes'!B:F, 5, 0) * D6 -> 4.5
B7: Brownie | C7: Ovos | D7: 4 | E7: =VLOOKUP(C7, 'Banco De Ingredientes'!B:F, 5, 0) * D7 -> 3.3333333
B8: Brownie | C8: Essência de Baunilha | D8: 10 | E8: =VLOOKUP(C8, 'Banco De Ingredientes'!B:F, 5, 0) * D8 -> 2
B9: Mousse de Chocolate | C9: Chocolate Meio Amargo | D9: 300 | E9: =VLOOKUP(C9, 'Banco De Ingredientes'!B:F, 5, 0) * D9 -> 13.5
B10: Mousse de Chocolate | C10: Creme de Leite | D10: 200 | E10: =VLOOKUP(C10, 'Banco De Ingredientes'!B:F, 5, 0) * D10 -> 4
B11: Mousse de Chocolate | C11: Leite Condensado | D11: 395 | E11: =VLOOKUP(C11, 'Banco De Ingredientes'!B:F, 5, 0) * D11 -> 6.5
B12: Mousse de Chocolate | C12: Gelatina Incolor | D12: 12 | E12: =VLOOKUP(C12, 'Banco De Ingredientes'!B:F, 5, 0) * D12 -> 2.25

Sheet Precificação Final
B2: Nome do Doce | C2: Custo Total dos Ingredientes | D2: Custos Fixos e Embalagem | E2: Margem de Lucro Esperada (%) | F2: Valor da Receita | G2: Rendimento (Unid.) | H2: Preço por Unid.
B3: Brownie | C3: =SUMIFS('Ficha Técnica (A Receita)'!E:E, 'Ficha Técnica (A Receita)'!B:B, B3) -> 24.373333 | D3: 3 | E3: 0.5 | F3: =(C3+D3)*(1+E3) -> 41.06 | G3: 10 | H3: =F3/G3 -> 4.106
B4: Mousse de Chocolate | C4: =SUMIFS('Ficha Técnica (A Receita)'!E:E, 'Ficha Técnica (A Receita)'!B:B, B4) -> 26.25 | D4: 3 | E4: 0.6 | F4: =(C4+D4)*(1+E4) -> 46.8 | G4: 6 | H4: =F4/G4 -> 7.8
